MANIFEST.in
README.md
setup.cfg
setup.py
redis_netlock/__init__.py
redis_netlock.egg-info/PKG-INFO
redis_netlock.egg-info/SOURCES.txt
redis_netlock.egg-info/dependency_links.txt
redis_netlock.egg-info/requires.txt
redis_netlock.egg-info/top_level.txt