Metadata-Version: 1.1
Name: redis-netlock
Version: 1.6
Summary: 一个用redis做的分布式锁，含有超时及重试机制.
Home-page: http://xiaorui.cc/
Author: ruifengyun
Author-email: rfyiamcool@163.com
License: MIT
Keywords: redis lock distributed,fengyun
Platform: Any
Classifier: Development Status :: 5 - Production/Stable
Classifier: Intended Audience :: Developers
Classifier: License :: OSI Approved :: BSD License
Classifier: Operating System :: OS Independent
Classifier: Programming Language :: Python
Classifier: Topic :: Software Development :: Libraries :: Python Modules
